datugokun/__init__.py
datugokun/datugokugpt.py
datugokugpt-0.1.0.dist-info/METADATA
datugokugpt-0.1.0.dist-info/WHEEL
datugokugpt-0.1.0.dist-info/top_level.txt
datugokugpt-0.1.0.dist-info/RECORD
