Metadata-Version: 2.1
Name: datugokugpt
Version: 0.1.0
Summary: Python wrapper for the DatugokuGPT API
Home-page: https://github.com/syo33331/datugokun
Author: Syo
Author-email: syojp9999@gmail.com
Classifier: Development Status :: 3 - Alpha
Classifier: Intended Audience :: Developers
Classifier: Programming Language :: Python :: 3
Classifier: Programming Language :: Python :: 3.7
Classifier: Programming Language :: Python :: 3.8
Classifier: Programming Language :: Python :: 3.9
Classifier: License :: OSI Approved :: MIT License
Classifier: Operating System :: OS Independent
Requires-Python: >=3.6
Requires-Dist: requests
